LanLexer/Lexer.py
LanLexer/Lexer.pyi
LanLexer/__init__.py
LanLexer-0.0.0.dist-info/LICENSE
LanLexer-0.0.0.dist-info/METADATA
LanLexer-0.0.0.dist-info/WHEEL
LanLexer-0.0.0.dist-info/top_level.txt
LanLexer-0.0.0.dist-info/RECORD
