Metadata-Version: 2.1
Name: LanLexer
Version: 0.0.0
Summary: One of the LanKit library tools is the lexer
Author-email: Markada <markada.py@gmail.com>
License: MIT License
Keywords: Markada,BNF,language,create,parser,lexer,LanKit
Classifier: Programming Language :: Python :: 3
Classifier: License :: OSI Approved :: MIT License
Classifier: Development Status :: 4 - Beta
Classifier: Natural Language :: Russian
Classifier: Operating System :: OS Independent
Requires-Python: >=3.10
License-File: LICENSE
